LICENSE
README.rst
minipg.py
pyproject.toml
setup.py
minipg.egg-info/PKG-INFO
minipg.egg-info/SOURCES.txt
minipg.egg-info/dependency_links.txt
minipg.egg-info/top_level.txt