Metadata-Version: 2.1
Name: minipg
Version: 0.10.1
Summary: Yet another PostgreSQL database driver
Home-page: https://github.com/nakagami/minipg/
Author: Hajime Nakagami
Author-email: Hajime Nakagami <nakagami@gmail.com>
License: The MIT License (MIT)
Project-URL: Homepage, https://github.com/nakagami/minipg/
Keywords: PostgreSQL
Classifier: Development Status :: 4 - Beta
Classifier: License :: OSI Approved :: MIT License
Classifier: Operating System :: OS Independent
Classifier: Programming Language :: Python
Classifier: Programming Language :: Python :: 3
Classifier: Topic :: Database
License-File: LICENSE
